LICENSE
README.md
pyproject.toml
setup.cfg
setup.py
dbt_airflow_factory/__init__.py
dbt_airflow_factory/airflow_dag_factory.py
dbt_airflow_factory/config_utils.py
dbt_airflow_factory/ingestion.py
dbt_airflow_factory.egg-info/PKG-INFO
dbt_airflow_factory.egg-info/SOURCES.txt
dbt_airflow_factory.egg-info/dependency_links.txt
dbt_airflow_factory.egg-info/not-zip-safe
dbt_airflow_factory.egg-info/requires.txt
dbt_airflow_factory.egg-info/top_level.txt
dbt_airflow_factory/cosmos/__init__.py
dbt_airflow_factory/cosmos/config_translator.py
dbt_airflow_factory/cosmos/execution_config_builder.py
dbt_airflow_factory/cosmos/operator_args_builder.py
dbt_airflow_factory/cosmos/profile_config_builder.py
dbt_airflow_factory/cosmos/project_config_builder.py
dbt_airflow_factory/notifications/__init__.py
dbt_airflow_factory/notifications/handler.py
dbt_airflow_factory/notifications/ms_teams_webhook_hook.py
dbt_airflow_factory/notifications/ms_teams_webhook_operator.py
tests/test_cosmos_config_translator.py
tests/test_cosmos_execution_config_builder.py
tests/test_cosmos_operator_args_builder.py
tests/test_cosmos_profile_config_builder.py
tests/test_cosmos_project_config_builder.py
tests/test_dag_factory.py
tests/test_notifications.py