Metadata-Version: 2.4
Name: dbt-airflow-factory
Version: 1.0.0
Summary: Library to convert DBT manifest metadata to Airflow tasks
Home-page: https://github.com/getindata/dbt-airflow-factory/
Author: Piotr Pekala
Author-email: piotr.pekala@getindata.com
License: Apache Software License (Apache 2.0)
Keywords: dbt airflow manifest parser python
Classifier: Development Status :: 5 - Production/Stable
Classifier: Programming Language :: Python :: 3.9
Classifier: Programming Language :: Python :: 3.10
Classifier: Programming Language :: Python :: 3.11
Classifier: Programming Language :: Python :: 3.12
Requires-Python: >=3.9
License-File: LICENSE
Requires-Dist: pytimeparse<2,>=1.1
Requires-Dist: astronomer-cosmos<2.0,>=1.10.0
Requires-Dist: apache-airflow<3,>=2.5
Requires-Dist: apache-airflow-providers-cncf-kubernetes
Requires-Dist: apache-airflow-providers-docker
Requires-Dist: apache-airflow-providers-slack
Requires-Dist: apache-airflow-providers-airbyte>=3.1
Provides-Extra: tests
Requires-Dist: pytest<7.0.0,>=6.2.2; extra == "tests"
Requires-Dist: pytest-cov<3.0.0,>=2.8.0; extra == "tests"
Requires-Dist: tox==3.21.1; extra == "tests"
Requires-Dist: pre-commit==2.9.3; extra == "tests"
Requires-Dist: pandas<2.0.0,>=1.2.5; extra == "tests"
Provides-Extra: docs
Requires-Dist: sphinx==4.3.1; extra == "docs"
Requires-Dist: sphinx-rtd-theme==1.0.0; extra == "docs"
Requires-Dist: sphinx-click<3.1,>=3.0; extra == "docs"
Requires-Dist: myst-parser<0.17,>=0.16; extra == "docs"
Requires-Dist: docutils<0.17; extra == "docs"
Dynamic: author
Dynamic: author-email
Dynamic: classifier
Dynamic: description
Dynamic: description-content-type
Dynamic: home-page
Dynamic: keywords
Dynamic: license
Dynamic: license-file
Dynamic: provides-extra
Dynamic: requires-dist
Dynamic: requires-python
Dynamic: summary
